enthusiast_source_medusa/__init__.py
enthusiast_source_medusa/source.py
enthusiast_source_medusa-1.2.1.dist-info/METADATA
enthusiast_source_medusa-1.2.1.dist-info/WHEEL
enthusiast_source_medusa-1.2.1.dist-info/licenses/LICENCE.md
enthusiast_source_medusa-1.2.1.dist-info/RECORD
